contentmonster/__init__.py
contentmonster/const.py
contentmonster/settings.example.ini
contentmonster/worker.py
contentmonster/classes/__init__.py
contentmonster/classes/chunk.py
contentmonster/classes/config.py
contentmonster/classes/connection.py
contentmonster/classes/database.py
contentmonster/classes/directory.py
contentmonster/classes/doghandler.py
contentmonster/classes/file.py
contentmonster/classes/logger.py
contentmonster/classes/remotefile.py
contentmonster/classes/retry.py
contentmonster/classes/shorethread.py
contentmonster/classes/vessel.py
contentmonster/classes/vesselthread.py
contentmonster-0.0.6.dist-info/METADATA
contentmonster-0.0.6.dist-info/WHEEL
contentmonster-0.0.6.dist-info/licenses/LICENSE
contentmonster-0.0.6.dist-info/RECORD
