Metadata-Version: 2.1
Name: contentmonster
Version: 0.0.6
Summary: File replicator
Project-URL: Homepage, https://kumig.it/kumisystems/contentmonster
Project-URL: Bug Tracker, https://kumig.it/kumisystems/contentmonster/issues
Author-email: "Kumi Systems e.U." <office@kumi.systems>
License: Copyright (c) 2021-2022 Kumi Systems e.U. <office@kumi.systems>
License-File: LICENSE
Classifier: License :: OSI Approved :: MIT License
Classifier: Operating System :: POSIX :: Linux
Classifier: Programming Language :: Python :: 3
Requires-Python: >=3.8
Requires-Dist: paramiko
Requires-Dist: watchdog
